notifsh/__init__.py
notifsh/client.py
notifsh/constants.py
notifsh/errors.py
notifsh/events.py
notifsh/types.py
notifsh-0.2.1.dist-info/METADATA
notifsh-0.2.1.dist-info/WHEEL
notifsh-0.2.1.dist-info/RECORD
