Metadata-Version: 2.4
Name: notifsh
Version: 0.2.1
Summary: Python SDK for notif.sh event hub
Project-URL: Homepage, https://notif.sh
Project-URL: Documentation, https://docs.notif.sh
Project-URL: Repository, https://github.com/filipexyz/notif
Author-email: "notif.sh" <hello@notif.sh>
License-Expression: MIT
Keywords: async,events,notif,notifsh,pubsub,webhooks,websocket
Classifier: Development Status :: 4 - Beta
Classifier: Framework :: AsyncIO
Classifier: Intended Audience :: Developers
Classifier: License :: OSI Approved :: MIT License
Classifier: Programming Language :: Python :: 3
Classifier: Programming Language :: Python :: 3.11
Classifier: Programming Language :: Python :: 3.12
Classifier: Programming Language :: Python :: 3.13
Classifier: Topic :: Internet :: WWW/HTTP
Classifier: Typing :: Typed
Requires-Python: >=3.11
Requires-Dist: httpx>=0.27.0
Requires-Dist: websockets>=12.0
Provides-Extra: dev
Requires-Dist: pytest-asyncio>=0.24.0; extra == 'dev'
Requires-Dist: pytest-cov>=5.0.0; extra == 'dev'
Requires-Dist: pytest>=8.0.0; extra == 'dev'
